CHANGES.txt
LICENSE.txt
MANIFEST.in
README.md
requirements.txt
setup.py
spotipy/__init__.py
spotipy/client.py
spotipy/oauth2.py
spotipy/util.py
spotipy_homeassistant.egg-info/PKG-INFO
spotipy_homeassistant.egg-info/SOURCES.txt
spotipy_homeassistant.egg-info/dependency_links.txt
spotipy_homeassistant.egg-info/requires.txt
spotipy_homeassistant.egg-info/top_level.txt