Metadata-Version: 1.0
Name: spotipy-homeassistant
Version: 2.4.4.dev1
Summary: simple client for the Spotify Web API
Home-page: http://spotipy.readthedocs.org/
Author: @plamere
Author-email: paul@echonest.com
License: LICENSE.txt
Platform: UNKNOWN
